piebedrock/__init__.py
piebedrock/__main__.py
piebedrock/buffer.py
piebedrock/const.py
piebedrock/jwt.py
piebedrock/server.py
piebedrock/utils.py
piebedrock/packets/__init__.py
piebedrock/packets/disconnect.py
piebedrock/packets/login.py
piebedrock/packets/packet.py
piebedrock/packets/play_status.py
piebedrock/packets/resource_packs_info.py
piebedrock/packets/server_client_handshake.py
PieBedrock-1.0.4.1.dist-info/LICENSE
PieBedrock-1.0.4.1.dist-info/METADATA
PieBedrock-1.0.4.1.dist-info/WHEEL
PieBedrock-1.0.4.1.dist-info/top_level.txt
PieBedrock-1.0.4.1.dist-info/RECORD
