Metadata-Version: 2.1
Name: PieBedrock
Version: 1.0.4.1
Author: LapisMYT, andiricum2, SixpennyYard, UCYT5040
License: GNU GENERAL PUBLIC LICENSE
Keywords: python,python3,raknet,rak-net,mcpe,bedrock,rak_net,piemc,pieraknet,piebedrock,bedrock-protocol,mineceaft-bedrock,network,protocol
Classifier: Development Status :: 3 - Alpha
Classifier: License :: OSI Approved :: GNU General Public License v3 (GPLv3)
Classifier: Programming Language :: Python :: 3.11
Classifier: Topic :: Internet
Classifier: Topic :: Games/Entertainment
Classifier: Topic :: Software Development :: Libraries :: Python Modules
Classifier: Topic :: System :: Networking
License-File: LICENSE
Requires-Dist: PieRakNet >=1.0.6
Requires-Dist: PyJWT
Requires-Dist: NBT
